x_console/__init__.py
x_console/cli_manager.py
x_console/utils/__init__.py
x_console/utils/cache.py
x_console/utils/localizer.py
x_console/utils/translator.py
x_console-0.1.2.dist-info/licenses/LICENSE
x_console-0.1.2.dist-info/METADATA
x_console-0.1.2.dist-info/WHEEL
x_console-0.1.2.dist-info/top_level.txt
x_console-0.1.2.dist-info/RECORD
