Metadata-Version: 2.4
Name: x_console
Version: 0.1.2
Summary: Class for nice and easy user interaction, with coloring and automatic translation support
Home-page: http://github.com/puntorigen/x_console
Author: Pablo Schaffner
Author-email: pablo@puntorigen.com
Classifier: Programming Language :: Python :: 3
Classifier: License :: OSI Approved :: MIT License
Classifier: Operating System :: OS Independent
Requires-Python: >=3.7, <4
License-File: LICENSE
Requires-Dist: rich
Requires-Dist: rich_click
Requires-Dist: simple_term_menu
Requires-Dist: yaspin
Requires-Dist: polib
Provides-Extra: online
Requires-Dist: lingua-language-detector; extra == "online"
Requires-Dist: deep_translator; extra == "online"
Provides-Extra: offline
Requires-Dist: lingua-language-detector; extra == "offline"
Requires-Dist: easynmt; extra == "offline"
Provides-Extra: full
Requires-Dist: lingua-language-detector; extra == "full"
Requires-Dist: deep_translator; extra == "full"
Requires-Dist: easynmt; extra == "full"
Dynamic: author
Dynamic: author-email
Dynamic: classifier
Dynamic: description
Dynamic: description-content-type
Dynamic: home-page
Dynamic: license-file
Dynamic: provides-extra
Dynamic: requires-dist
Dynamic: requires-python
Dynamic: summary
